[
  {
    "name": "React JS",
    "url": "https://img.icons8.com/color/192/000000/react-native.png"
  },
  {
    "name": "MySQL",
    "url": "https://img.icons8.com/fluency/192/000000/mysql-logo.png"
  },
  {
    "name": "MongoDB",
    "url": "https://img.icons8.com/color/192/000000/mongodb.png"
  },
  {
    "name": "CSS",
    "url": "https://img.icons8.com/color/192/000000/css3.png"
  },
  {
    "name": "Tailwind",
    "url": "https://img.icons8.com/color/192/000000/tailwindcss.png"
  },
  {
    "name": "Spring Boot",
    "url": "https://img.icons8.com/?size=100&id=90519&format=png&color=000000"
  },
  {
    "name": "Docker",
    "url": "https://img.icons8.com/color/344/docker.png"
  },
  {
    "name": "Jenkins",
    "url": "https://img.icons8.com/color/344/jenkins.png"
  },
  {
    "name": "Django",
    "url": "https://img.icons8.com/color/344/django.png"
  },
  {
    "name": "Python",
    "url": "https://img.icons8.com/color/344/python.png"
  },
  {
    "name": "PostgreSQL",
    "url": "https://img.icons8.com/?size=100&id=LwQEs9KnDgIo&format=png&color=000000"
  },
  {
    "name": "Bootstrap",
    "url": "https://img.icons8.com/color/192/000000/bootstrap.png"
  },
  {
    "name": "Material UI",
    "url": "https://img.icons8.com/color/344/material-ui.png"
  },
  {
    "name": "HTML",
    "url": "https://img.icons8.com/color/192/000000/html-5.png"
  },
  {
    "name": "Node JS",
    "url": "https://img.icons8.com/color/192/000000/nodejs.png"
  },
  {
    "name": "Express JS",
    "url": "https://cdn.jsdelivr.net/gh/devicons/devicon/icons/express/express-original.svg"
  },

  {
    "name": "JavaScript",
    "url": "https://img.icons8.com/color/192/000000/javascript.png"
  },

  {
    "name": "Next JS",
    "url": "https://www.svgrepo.com/show/354112/nextjs.svg"
  },
  {
    "name": "Gatsby JS",
    "url": "https://img.icons8.com/?size=100&id=VKNg2JKMVsS9&format=png&color=000000"
  },
  {
    "name": "TypeScript",
    "url": "https://img.icons8.com/color/192/000000/typescript.png"
  },
  {
    "name": "C++",
    "url": "https://img.icons8.com/color/192/000000/c-plus-plus-logo.png"
  },
  {
    "name": "Java",
    "url": "https://img.icons8.com/color/192/000000/java-coffee-cup-logo.png"
  },

  {
    "name": "AWS",
    "url": "https://img.icons8.com/color/192/000000/amazon-web-services.png"
  },

  {
    "name": "Git",
    "url": "https://img.icons8.com/color/192/000000/git.png"
  },
  {
    "name": "GitHub Actions",
    "url": "https://avatars.githubusercontent.com/u/44036562?s=200&v=4"
  },
  {
    "name": "Heroku",
    "url": "https://img.icons8.com/color/480/000000/heroku.png"
  },
  {
    "name": "Netlify",
    "url": "https://img.icons8.com/external-tal-revivo-color-tal-revivo/384/000000/external-netlify-a-cloud-computing-company-that-offers-hosting-and-serverless-backend-services-for-static-websites-logo-color-tal-revivo.png"
  },
  {
    "name": "Photoshop",
    "url": "https://img.icons8.com/color/192/000000/adobe-photoshop.png"
  },
  {
    "name": "Adobe XD",
    "url": "https://img.icons8.com/color/192/000000/adobe-xd.png"
  },
  {
    "name": "Figma",
    "url": "https://img.icons8.com/color/192/000000/figma.png"
  },
  {
    "name": "InDesign",
    "url": "https://img.icons8.com/color/192/000000/adobe-indesign.png"
  },
  {
    "name": "Illustrator",
    "url": "https://img.icons8.com/color/192/000000/adobe-illustrator.png"
  }
]
